archon/__init__.py
archon/cli.py
archon/db.py
archon/engine.py
archon/events.py
archon/geo.py
archon/models.py
archon/scoring.py
archon/vekn.py
archon/app/__init__.py
archon/app/__main__.py
archon/app/dependencies.py
archon/app/main.py
archon/app/api/__init__.py
archon/app/api/admin.py
archon/app/api/league.py
archon/app/api/tournament.py
archon/app/api/vekn.py
archon/app/html/__init__.py
archon/app/html/website.py
archon/geodata/cities.json
archon/geodata/countries.json
archon/img/black-chantry-icon.webp
archon/img/favicon.ico
archon/static/admin.js
archon/static/admin.js.map
archon/static/base.js
archon/static/base.js.map
archon/static/bootstrap-icons.019ba25e.woff
archon/static/bootstrap-icons.20664353.woff
archon/static/bootstrap-icons.632499a9.woff2
archon/static/bootstrap-icons.dc6e4a26.woff2
archon/static/checkin.js
archon/static/checkin.js.map
archon/static/d.js
archon/static/d.js.map
archon/static/layout.css
archon/static/layout.css.map
archon/static/league_display.js
archon/static/league_display.js.map
archon/static/league_list.js
archon/static/league_list.js.map
archon/static/login.js
archon/static/login.js.map
archon/static/member_display.js
archon/static/member_display.js.map
archon/static/member_list.js
archon/static/member_list.js.map
archon/static/profile.js
archon/static/profile.js.map
archon/static/qr-scanner-worker.min.9ca2d6bd.js
archon/static/qr-scanner-worker.min.9ca2d6bd.js.map
archon/static/qr-scanner-worker.min.a7f55b2c.js
archon/static/qr-scanner-worker.min.a7f55b2c.js.map
archon/static/seating.js
archon/static/seating.js.map
archon/static/topnav.js
archon/static/topnav.js.map
archon/static/tournament_display.js
archon/static/tournament_display.js.map
archon/static/tournament_list.js
archon/static/tournament_list.js.map
archon/static/tournament/console.js
archon/static/tournament/console.js.map
archon/templates/401.html.j2
archon/templates/403.html.j2
archon/templates/404.html.j2
archon/templates/error.html.j2
vtes_archon-0.64.dist-info/licenses/LICENSE
vtes_archon-0.64.dist-info/METADATA
vtes_archon-0.64.dist-info/WHEEL
vtes_archon-0.64.dist-info/entry_points.txt
vtes_archon-0.64.dist-info/top_level.txt
vtes_archon-0.64.dist-info/RECORD
