Metadata-Version: 2.4
Name: vtes-archon
Version: 0.64
Summary: VTES tournament management
Author: VEKN
License-Expression: MIT
Project-URL: Repository, https://github.com/vtes-biased/archon
Keywords: vtes,Vampire: The Eternal Struggle,CCG,Tournament
Classifier: Programming Language :: Python :: 3.11
Classifier: Programming Language :: Python :: 3.12
Classifier: Programming Language :: Python :: 3.13
Classifier: Development Status :: 3 - Alpha
Classifier: Natural Language :: English
Classifier: Operating System :: OS Independent
Classifier: Framework :: FastAPI
Classifier: Topic :: Internet :: WWW/HTTP :: WSGI :: Application
Requires-Python: >=3.11
License-File: LICENSE
Requires-Dist: aiohttp
Requires-Dist: fastapi[standard]
Requires-Dist: fastapi-mail
Requires-Dist: itsdangerous
Requires-Dist: jinja2
Requires-Dist: krcg>=4.4
Requires-Dist: orjson
Requires-Dist: psycopg[binary,pool]
Requires-Dist: pyjwt
Requires-Dist: python-dotenv
Requires-Dist: typer
Requires-Dist: uvicorn
Provides-Extra: dev
Requires-Dist: ansible; extra == "dev"
Requires-Dist: black; extra == "dev"
Requires-Dist: build; extra == "dev"
Requires-Dist: check-manifest; extra == "dev"
Requires-Dist: debugpy; extra == "dev"
Requires-Dist: ipython; extra == "dev"
Requires-Dist: pytest; extra == "dev"
Requires-Dist: ruff; extra == "dev"
Requires-Dist: setuptools-scm; extra == "dev"
Requires-Dist: twine; extra == "dev"
Dynamic: license-file
